training_stats/__init__.py
training_stats/cuvette.py
training_stats/gpxfile.py
training_stats/half_hour_test.py
training_stats/hrm.py
training_stats/test_get_hr_measurements.py
training_stats/test_interpolate.py
training_stats/utils.py
training_stats-0.2.0.dist-info/DESCRIPTION.rst
training_stats-0.2.0.dist-info/METADATA
training_stats-0.2.0.dist-info/RECORD
training_stats-0.2.0.dist-info/WHEEL
training_stats-0.2.0.dist-info/metadata.json
training_stats-0.2.0.dist-info/top_level.txt
