Metadata-Version: 2.0
Name: training-stats
Version: 0.2.0
Summary: Training Stats
Home-page: https://github.com/salwator/training_stats
Author: Jakub Draganek
Author-email: jakub.draganek@gmail.com
License: UNKNOWN
Platform: UNKNOWN
Requires-Python: >=3.4
Requires-Dist: numpy
